hqstage.cpython-313-x86_64-linux-gnu.so
hqstage.pyi
hqstage/__init__.pyi
hqstage.build/.gitignore
hqstage-0.9.3.dist-info/METADATA
hqstage-0.9.3.dist-info/WHEEL
hqstage-0.9.3.dist-info/entry_points.txt
hqstage-0.9.3.dist-info/top_level.txt
hqstage-0.9.3.dist-info/RECORD
hqstage-0.9.3.dist-info/licenses/LICENSE
