Metadata-Version: 2.4
Name: hqstage
Version: 0.9.3
Summary: HQStage is a lightweight tool for installing and using HQS software.
Author-email: HQS Quantum Simulation GmbH <info@quantumsimulations.de>
Maintainer-email: Sebastian Zanker <sebastian.zanker@quantumsimulations.de>
License: HQS Terms of use
Project-URL: Homepage, https://cloud.quantumsimulations.de
Project-URL: Documentation, https://docs.cloud.quantumsimulations.de
Project-URL: HQS, https://quantumsimulations.de
Classifier: Intended Audience :: End Users/Desktop
Classifier: Intended Audience :: Healthcare Industry
Classifier: Intended Audience :: Information Technology
Classifier: Intended Audience :: Science/Research
Classifier: License :: Other/Proprietary License
Classifier: Operating System :: MacOS
Classifier: Operating System :: POSIX :: Linux
Classifier: Programming Language :: Python
Classifier: Topic :: Scientific/Engineering
Classifier: Topic :: Scientific/Engineering :: Chemistry
Classifier: Topic :: Scientific/Engineering :: Mathematics
Classifier: Topic :: Scientific/Engineering :: Medical Science Apps.
Classifier: Topic :: Scientific/Engineering :: Physics
Classifier: Topic :: Scientific/Engineering :: Quantum Computing
Requires-Python: >=3.10
License-File: LICENSE
Requires-Dist: aiohttp
Requires-Dist: uv>=0.1.36
Requires-Dist: click>=8.0
Requires-Dist: diskcache
Requires-Dist: platformdirs
Requires-Dist: configparser
Requires-Dist: tomli
Requires-Dist: tomli-w
Requires-Dist: pynacl
Requires-Dist: py-machineid
Requires-Dist: pydantic
Requires-Dist: pypi-simple
Requires-Dist: requests
Requires-Dist: shellingham
Requires-Dist: tqdm
Requires-Dist: urllib3>=2.0
Requires-Dist: semver
Provides-Extra: tests
Requires-Dist: coverage; extra == "tests"
Requires-Dist: pytest; extra == "tests"
Provides-Extra: dev
Requires-Dist: bandit; extra == "dev"
Requires-Dist: black; extra == "dev"
Requires-Dist: mypy; extra == "dev"
Requires-Dist: ruff; extra == "dev"
Requires-Dist: types-requests; extra == "dev"
Provides-Extra: docs
Requires-Dist: sphinx; extra == "docs"
Requires-Dist: sphinx_rtd_theme; extra == "docs"
Requires-Dist: nbsphinx; extra == "docs"
Dynamic: license-file
